Verilog_fundamentals/Full_subractor/module.v
// full_subtractor.v
module full_subtractor (
    input  wire a,      // Minuend
    input  wire b,      // Subtrahend
    input  wire bin,    // Borrow-in
    output wire diff,   // Difference
    output wire bout    // Borrow-out
);

    // Continuous assignment statements for dataflow modeling
    assign diff = a ^ b ^ bin;
    assign bout = (~a & b) | (~(a ^ b) & bin);

endmodule

Verilog_fundamentals/Full_subractor/testbench.v
// full_subtractor_tb.v
`timescale 1ns / 1ps

module full_subtractor_tb;

    // Inputs are declared as registers (reg) to hold values
    reg a;
    reg b;
    reg bin;

    // Outputs are declared as wires
    wire diff;
    wire bout;

    // Instantiate the Unit Under Test (UUT)
    full_subtractor uut (
        .a(a),.b(b),.bin(bin),.diff(diff),.bout(bout));

    initial begin
        // Setup dumpfiles for Icarus Verilog simulation viewing
        $dumpfile("full_subtractor_wave.vcd");
        $dumpvars(0, full_subtractor_tb);

        // Display headers in the console output
        $display("Time\t A \t B \t Bin \t Diff \t Bout");
        $display("---------------------------------------------");
        
        // Monitor outputs automatically on any signal change
        $monitor("%4pt\t %b \t %b \t  %b  \t  %b   \t  %b", $time, a, b, bin, diff, bout);

        // Test all 8 combinations sequentially with 10ns intervals
        a = 0; b = 0; bin = 0; #10;
        a = 0; b = 0; bin = 1; #10;
        a = 0; b = 1; bin = 0; #10;
        a = 0; b = 1; bin = 1; #10;
        a = 1; b = 0; bin = 0; #10;
        a = 1; b = 0; bin = 1; #10;
        a = 1; b = 1; bin = 0; #10;
        a = 1; b = 1; bin = 1; #10;

        // End the simulation
        $finish;
    end

endmodule

Verilog_fundamentals/Full_subractor/full_subtractor_wave.vcd
$date
	Sat Sep  5 23:25:10 2026
$end
$version
	Icarus Verilog
$end
$timescale
	1ps
$end
$scope module full_subtractor_tb $end
$var wire 1 ! diff $end
$var wire 1 " bout $end
$var reg 1 # a $end
$var reg 1 $ b $end
$var reg 1 % bin $end
$scope module uut $end
$var wire 1 # a $end
$var wire 1 $ b $end
$var wire 1 % bin $end
$var wire 1 " bout $end
$var wire 1 ! diff $end
$upscope $end
$upscope $end
$enddefinitions $end
$comment Show the parameter values. $end
$dumpall
$end
#0
$dumpvars
0%
0$
0#
0"
0!
$end
#10000
1"
1!
1%
#20000
0%
1$
#30000
0!
1%
#40000
0"
1!
0%
0$
1#
#50000
0!
1%
#60000
0%
1$
#70000
1"
1!
1%
