Always_blck/mux_81/module.v
module mux8to1 (
    input  wire [7:0] I,
    input  wire [2:0] S,
    output reg        Y
);

always @(*) begin

    case (S)

        3'b000: Y = I[0];
        3'b001: Y = I[1];
        3'b010: Y = I[2];
        3'b011: Y = I[3];
        3'b100: Y = I[4];
        3'b101: Y = I[5];
        3'b110: Y = I[6];
        3'b111: Y = I[7];

        default: Y = 1'b0;

    endcase

end

endmodule

Always_blck/mux_81/testbench.v
`timescale 1ns/1ps

module mux8to1_tb;

    reg  [7:0] I;
    reg  [2:0] S;

    wire Y;

    // Instantiate DUT
    mux8to1 uut (
        .I(I),
        .S(S),
        .Y(Y)
    );

    initial begin

        // Create waveform
        $dumpfile("mux8to1.vcd");
        $dumpvars(0, mux8to1_tb);

        $monitor("Time=%0t | I=%b | S=%b | Y=%b",
                 $time, I, S, Y);

        // Input pattern
        I = 8'b10110110;

        // Select I0
        S = 3'b000;
        #10;

        // Select I1
        S = 3'b001;
        #10;

        // Select I2
        S = 3'b010;
        #10;

        // Select I3
        S = 3'b011;
        #10;

        // Select I4
        S = 3'b100;
        #10;

        // Select I5
        S = 3'b101;
        #10;

        // Select I6
        S = 3'b110;
        #10;

        // Select I7
        S = 3'b111;
        #10;


        // Change input pattern
        I = 8'b11001001;

        S = 3'b000;
        #10;

        S = 3'b001;
        #10;

        S = 3'b010;
        #10;

        S = 3'b011;
        #10;

        S = 3'b100;
        #10;

        S = 3'b101;
        #10;

        S = 3'b110;
        #10;

        S = 3'b111;
        #10;

        $finish;

    end

endmodule

Always_blck/mux_81/mux8to1.vcd
$date
	Tue Sep  8 19:37:19 2026
$end
$version
	Icarus Verilog
$end
$timescale
	1ps
$end
$scope module mux8to1_tb $end
$var wire 1 ! Y $end
$var reg 8 " I [7:0] $end
$var reg 3 # S [2:0] $end
$scope module uut $end
$var wire 8 $ I [7:0] $end
$var wire 3 % S [2:0] $end
$var reg 1 ! Y $end
$upscope $end
$upscope $end
$enddefinitions $end
$comment Show the parameter values. $end
$dumpall
$end
#0
$dumpvars
b0 %
b10110110 $
b0 #
b10110110 "
0!
$end
#10000
1!
b1 #
b1 %
#20000
b10 #
b10 %
#30000
0!
b11 #
b11 %
#40000
1!
b100 #
b100 %
#50000
b101 #
b101 %
#60000
0!
b110 #
b110 %
#70000
1!
b111 #
b111 %
#80000
b0 #
b0 %
b11001001 "
b11001001 $
#90000
0!
b1 #
b1 %
#100000
b10 #
b10 %
#110000
1!
b11 #
b11 %
#120000
0!
b100 #
b100 %
#130000
b101 #
b101 %
#140000
1!
b110 #
b110 %
#150000
b111 #
b111 %
