Always_blck/Barrel_shifter/module.v
module barrel_shifter (
    input  wire [3:0] data,
    input  wire [1:0] shift,
    input  wire       direction,
    output reg  [3:0] result
);

always @(*) begin

    if (direction == 1'b0)
        // Shift left
        result = data << shift;

    else
        // Shift right
        result = data >> shift;

end

endmodule

Always_blck/Barrel_shifter/testbench.v
`timescale 1ns/1ps

module barrel_shifter_tb;

    reg  [3:0] data;
    reg  [1:0] shift;
    reg        direction;

    wire [3:0] result;

    // Instantiate the barrel shifter
    barrel_shifter uut (
        .data(data),
        .shift(shift),
        .direction(direction),
        .result(result)
    );

    initial begin

        // Create waveform
        $dumpfile("barrel_shifter.vcd");
        $dumpvars(0, barrel_shifter_tb);

        $monitor("Time=%0t | Data=%b | Shift=%b | Direction=%b | Result=%b",
                 $time, data, shift, direction, result);

        // --------------------------------
        // LEFT SHIFT TESTS
        // --------------------------------

        data = 4'b1011;
        shift = 2'b00;
        direction = 1'b0;
        #10;

        data = 4'b1011;
        shift = 2'b01;
        direction = 1'b0;
        #10;

        data = 4'b1011;
        shift = 2'b10;
        direction = 1'b0;
        #10;

        data = 4'b1011;
        shift = 2'b11;
        direction = 1'b0;
        #10;


        // --------------------------------
        // RIGHT SHIFT TESTS
        // --------------------------------

        data = 4'b1011;
        shift = 2'b00;
        direction = 1'b1;
        #10;

        data = 4'b1011;
        shift = 2'b01;
        direction = 1'b1;
        #10;

        data = 4'b1011;
        shift = 2'b10;
        direction = 1'b1;
        #10;

        data = 4'b1011;
        shift = 2'b11;
        direction = 1'b1;
        #10;

        $finish;

    end

endmodule

Always_blck/Barrel_shifter/barrel_shifter.vcd
$date
	Mon Sep  7 23:08:07 2026
$end
$version
	Icarus Verilog
$end
$timescale
	1ps
$end
$scope module barrel_shifter_tb $end
$var wire 4 ! result [3:0] $end
$var reg 4 " data [3:0] $end
$var reg 1 # direction $end
$var reg 2 $ shift [1:0] $end
$scope module uut $end
$var wire 4 % data [3:0] $end
$var wire 1 # direction $end
$var wire 2 & shift [1:0] $end
$var reg 4 ' result [3:0] $end
$upscope $end
$upscope $end
$enddefinitions $end
$comment Show the parameter values. $end
$dumpall
$end
#0
$dumpvars
b1011 '
b0 &
b1011 %
b0 $
0#
b1011 "
b1011 !
$end
#10000
b110 !
b110 '
b1 $
b1 &
#20000
b1100 !
b1100 '
b10 $
b10 &
#30000
b1000 !
b1000 '
b11 $
b11 &
#40000
b1011 !
b1011 '
1#
b0 $
b0 &
#50000
b101 !
b101 '
b1 $
b1 &
#60000
b10 !
b10 '
b10 $
b10 &
#70000
b1 !
b1 '
b11 $
b11 &
