Always_blck/Gray_binary/module.v
module gray_to_binary (
    input  wire [3:0] gray,
    output reg  [3:0] binary
);

always @(*) begin

    binary[3] = gray[3];
    binary[2] = binary[3] ^ gray[2];
    binary[1] = binary[2] ^ gray[1];
    binary[0] = binary[1] ^ gray[0];

end

endmodule

Always_blck/Gray_binary/testbench.v
`timescale 1ns/1ps

module gray_to_binary_tb;

    reg  [3:0] gray;
    wire [3:0] binary;

    // Instantiate DUT
    gray_to_binary uut (
        .gray(gray),
        .binary(binary)
    );

    initial begin

        // Create waveform
        $dumpfile("gray_to_binary.vcd");
        $dumpvars(0, gray_to_binary_tb);

        $monitor("Time=%0t | Gray=%b | Binary=%b (%0d)",
                 $time, gray, binary, binary);

        // Test 0000
        gray = 4'b0000;
        #10;

        // Test 0001
        gray = 4'b0001;
        #10;

        // Test 0011
        gray = 4'b0011;
        #10;

        // Test 0010
        gray = 4'b0010;
        #10;

        // Test 0110
        gray = 4'b0110;
        #10;

        // Test 0111
        gray = 4'b0111;
        #10;

        // Test 0101
        gray = 4'b0101;
        #10;

        // Test 0100
        gray = 4'b0100;
        #10;

        // Test 1100
        gray = 4'b1100;
        #10;

        // Test 1101
        gray = 4'b1101;
        #10;

        // Test 1111
        gray = 4'b1111;
        #10;

        // Test 1110
        gray = 4'b1110;
        #10;

        // Test 1010
        gray = 4'b1010;
        #10;

        // Test 1011
        gray = 4'b1011;
        #10;

        // Test 1001
        gray = 4'b1001;
        #10;

        // Test 1000
        gray = 4'b1000;
        #10;

        $finish;

    end

endmodule

Always_blck/Gray_binary/gray_to_binary.vcd
$date
	Tue Sep  8 19:27:46 2026
$end
$version
	Icarus Verilog
$end
$timescale
	1ps
$end
$scope module gray_to_binary_tb $end
$var wire 4 ! binary [3:0] $end
$var reg 4 " gray [3:0] $end
$scope module uut $end
$var wire 4 # gray [3:0] $end
$var reg 4 $ binary [3:0] $end
$upscope $end
$upscope $end
$enddefinitions $end
$comment Show the parameter values. $end
$dumpall
$end
#0
$dumpvars
b0 $
b0 #
b0 "
b0 !
$end
#10000
b1 !
b1 $
b1 "
b1 #
#20000
b10 !
b10 $
b11 "
b11 #
#30000
b11 !
b11 $
b10 "
b10 #
#40000
b100 !
b100 $
b110 "
b110 #
#50000
b101 !
b101 $
b111 "
b111 #
#60000
b110 !
b110 $
b101 "
b101 #
#70000
b111 !
b111 $
b100 "
b100 #
#80000
b1000 !
b1000 $
b1100 "
b1100 #
#90000
b1001 !
b1001 $
b1101 "
b1101 #
#100000
b1010 !
b1010 $
b1111 "
b1111 #
#110000
b1011 !
b1011 $
b1110 "
b1110 #
#120000
b1100 !
b1100 $
b1010 "
b1010 #
#130000
b1101 !
b1101 $
b1011 "
b1011 #
#140000
b1110 !
b1110 $
b1001 "
b1001 #
#150000
b1111 !
b1111 $
b1000 "
b1000 #
