Verilog_fundamentals/2x1_mux/module.v
module mux_2x1 (input wire i0,i1,s,output wire y);
    assign y = s ? i1 : i0;

endmodule

Verilog_fundamentals/2x1_mux/testbench.v
`timescale 1ns / 1ps

module mux_2x1_tb;

    // Inputs (reg) to drive the design under test
    reg i0,i1,s;

    // Outputs (wire) to monitor the design
    wire y;

    // Instantiate the Design Under Test (DUT)
    mux_2x1 dut (
        .i0(i0),
        .i1(i1),
        .s(s),
        .y(y)
    );

    // Loop variable for test combinations
    integer i;

    initial begin
        // 1. Icarus Verilog specific waveform dumping commands
        $dumpfile("mux_dump.vcd"); // Creates the VCD file
        $dumpvars(0, mux_2x1_tb);  // Dumps all signals in this module

        // 2. Terminal monitoring setup
        $display("Time\t S \t I1 \t I0 \t Y");
        $display("---------------------------------");
        $monitor("%0dns\t %b \t %b \t %b \t %b", $time, s, i1, i0, y);

        // 3. Test vector generation loop (evaluates all 8 input states)
        for (i = 0; i < 8; i = i + 1) begin
            {s, i1, i0} = i; 
            #10; 
        end

        // End the simulation
        $finish;
    end

endmodule

Verilog_fundamentals/2x1_mux/mux_dump.vcd
$date
	Sun Sep  6 00:16:40 2026
$end
$version
	Icarus Verilog
$end
$timescale
	1ps
$end
$scope module mux_2x1_tb $end
$var wire 1 ! y $end
$var reg 1 " i0 $end
$var reg 1 # i1 $end
$var reg 1 $ s $end
$var integer 32 % i [31:0] $end
$scope module dut $end
$var wire 1 " i0 $end
$var wire 1 # i1 $end
$var wire 1 $ s $end
$var wire 1 ! y $end
$upscope $end
$upscope $end
$enddefinitions $end
$comment Show the parameter values. $end
$dumpall
$end
#0
$dumpvars
b0 %
0$
0#
0"
0!
$end
#10000
1!
1"
b1 %
#20000
0!
1#
0"
b10 %
#30000
1!
1"
b11 %
#40000
0!
1$
0#
0"
b100 %
#50000
1"
b101 %
#60000
1!
1#
0"
b110 %
#70000
1"
b111 %
#80000
b1000 %
