Always_blck/Binary_BCD/module.v
module binary_to_bcd (
    input  wire [3:0] binary,
    output reg  [7:0] bcd
);

always @(*) begin

    case (binary)

        4'b0000: bcd = 8'b0000_0000; // 0
        4'b0001: bcd = 8'b0000_0001; // 1
        4'b0010: bcd = 8'b0000_0010; // 2
        4'b0011: bcd = 8'b0000_0011; // 3
        4'b0100: bcd = 8'b0000_0100; // 4
        4'b0101: bcd = 8'b0000_0101; // 5
        4'b0110: bcd = 8'b0000_0110; // 6
        4'b0111: bcd = 8'b0000_0111; // 7
        4'b1000: bcd = 8'b0000_1000; // 8
        4'b1001: bcd = 8'b0000_1001; // 9
        4'b1010: bcd = 8'b0001_0000; // 10
        4'b1011: bcd = 8'b0001_0001; // 11
        4'b1100: bcd = 8'b0001_0010; // 12
        4'b1101: bcd = 8'b0001_0011; // 13
        4'b1110: bcd = 8'b0001_0100; // 14
        4'b1111: bcd = 8'b0001_0101; // 15

        default: bcd = 8'b0000_0000;

    endcase

end

endmodule

Always_blck/Binary_BCD/testbench.v
`timescale 1ns/1ps

module binary_to_bcd_tb;

    reg  [3:0] binary;
    wire [7:0] bcd;

    // Instantiate DUT
    binary_to_bcd uut (
        .binary(binary),
        .bcd(bcd)
    );

    initial begin

        // Create waveform
        $dumpfile("binary_to_bcd.vcd");
        $dumpvars(0, binary_to_bcd_tb);

        $monitor("Time=%0t | Binary=%b (%0d) | BCD=%b",
                 $time, binary, binary, bcd);

        // Test 0
        binary = 4'b0000;
        #10;

        // Test 1
        binary = 4'b0001;
        #10;

        // Test 5
        binary = 4'b0101;
        #10;

        // Test 9
        binary = 4'b1001;
        #10;

        // Test 10
        binary = 4'b1010;
        #10;

        // Test 11
        binary = 4'b1011;
        #10;

        // Test 12
        binary = 4'b1100;
        #10;

        // Test 13
        binary = 4'b1101;
        #10;

        // Test 14
        binary = 4'b1110;
        #10;

        // Test 15
        binary = 4'b1111;
        #10;

        $finish;

    end

endmodule

Always_blck/Binary_BCD/binary_to_bcd.vcd
$date
	Mon Sep  7 23:10:59 2026
$end
$version
	Icarus Verilog
$end
$timescale
	1ps
$end
$scope module binary_to_bcd_tb $end
$var wire 8 ! bcd [7:0] $end
$var reg 4 " binary [3:0] $end
$scope module uut $end
$var wire 4 # binary [3:0] $end
$var reg 8 $ bcd [7:0] $end
$upscope $end
$upscope $end
$enddefinitions $end
$comment Show the parameter values. $end
$dumpall
$end
#0
$dumpvars
b0 $
b0 #
b0 "
b0 !
$end
#10000
b1 !
b1 $
b1 "
b1 #
#20000
b101 !
b101 $
b101 "
b101 #
#30000
b1001 !
b1001 $
b1001 "
b1001 #
#40000
b10000 !
b10000 $
b1010 "
b1010 #
#50000
b10001 !
b10001 $
b1011 "
b1011 #
#60000
b10010 !
b10010 $
b1100 "
b1100 #
#70000
b10011 !
b10011 $
b1101 "
b1101 #
#80000
b10100 !
b10100 $
b1110 "
b1110 #
#90000
b10101 !
b10101 $
b1111 "
b1111 #
