Always_blck/ALU/module.v
module alu (
    input  wire [3:0] A,
    input  wire [3:0] B,
    input  wire [2:0] ALU_Sel,

    output reg  [3:0] Result,
    output reg        Carry,
    output reg        Zero
);

always @(*) begin

    // Default values
    Result = 4'b0000;
    Carry  = 1'b0;

    case (ALU_Sel)

        3'b000: begin
            // Addition
            {Carry, Result} = A + B;
        end

        3'b001: begin
            // Subtraction
            Result = A - B;
        end

        3'b010: begin
            // AND
            Result = A & B;
        end

        3'b011: begin
            // OR
            Result = A | B;
        end

        3'b100: begin
            // XOR
            Result = A ^ B;
        end

        3'b101: begin
            // NOT A
            Result = ~A;
        end

        3'b110: begin
            // Shift left
            Result = A << 1;
        end

        3'b111: begin
            // Shift right
            Result = A >> 1;
        end

        default: begin
            Result = 4'b0000;
            Carry  = 1'b0;
        end

    endcase

    // Zero flag
    if (Result == 4'b0000)
        Zero = 1'b1;
    else
        Zero = 1'b0;

end

endmodule

Always_blck/ALU/testbench.v
`timescale 1ns/1ps

module alu_tb;

    reg  [3:0] A;
    reg  [3:0] B;
    reg  [2:0] ALU_Sel;

    wire [3:0] Result;
    wire       Carry;
    wire       Zero;

    // Instantiate ALU
    alu uut (
        .A(A),
        .B(B),
        .ALU_Sel(ALU_Sel),
        .Result(Result),
        .Carry(Carry),
        .Zero(Zero)
    );

    initial begin

        // Create waveform file
        $dumpfile("alu.vcd");
        $dumpvars(0, alu_tb);

        // Display values
        $monitor("Time=%0t | A=%b | B=%b | Sel=%b | Result=%b | Carry=%b | Zero=%b",
                 $time, A, B, ALU_Sel, Result, Carry, Zero);

        // Addition
        A = 4'b0101;
        B = 4'b0011;
        ALU_Sel = 3'b000;
        #10;

        // Subtraction
        A = 4'b1000;
        B = 4'b0011;
        ALU_Sel = 3'b001;
        #10;

        // AND
        A = 4'b1100;
        B = 4'b1010;
        ALU_Sel = 3'b010;
        #10;

        // OR
        A = 4'b1100;
        B = 4'b1010;
        ALU_Sel = 3'b011;
        #10;

        // XOR
        A = 4'b1100;
        B = 4'b1010;
        ALU_Sel = 3'b100;
        #10;

        // NOT A
        A = 4'b1010;
        B = 4'b0000;
        ALU_Sel = 3'b101;
        #10;

        // Shift left
        A = 4'b0011;
        B = 4'b0000;
        ALU_Sel = 3'b110;
        #10;

        // Shift right
        A = 4'b1100;
        B = 4'b0000;
        ALU_Sel = 3'b111;
        #10;

        $finish;
    end

endmodule

Always_blck/ALU/alu.vcd
$date
	Mon Sep  7 23:06:57 2026
$end
$version
	Icarus Verilog
$end
$timescale
	1ps
$end
$scope module alu_tb $end
$var wire 1 ! Zero $end
$var wire 4 " Result [3:0] $end
$var wire 1 # Carry $end
$var reg 4 $ A [3:0] $end
$var reg 3 % ALU_Sel [2:0] $end
$var reg 4 & B [3:0] $end
$scope module uut $end
$var wire 4 ' A [3:0] $end
$var wire 3 ( ALU_Sel [2:0] $end
$var wire 4 ) B [3:0] $end
$var reg 1 # Carry $end
$var reg 4 * Result [3:0] $end
$var reg 1 ! Zero $end
$upscope $end
$upscope $end
$enddefinitions $end
$comment Show the parameter values. $end
$dumpall
$end
#0
$dumpvars
b1000 *
b11 )
b0 (
b101 '
b11 &
b0 %
b101 $
0#
b1000 "
0!
$end
#10000
b101 "
b101 *
b1 %
b1 (
b1000 $
b1000 '
#20000
b1000 "
b1000 *
b10 %
b10 (
b1010 &
b1010 )
b1100 $
b1100 '
#30000
b1110 "
b1110 *
b11 %
b11 (
#40000
b110 "
b110 *
b100 %
b100 (
#50000
b101 "
b101 *
b101 %
b101 (
b0 &
b0 )
b1010 $
b1010 '
#60000
b110 "
b110 *
b110 %
b110 (
b11 $
b11 '
#70000
b110 "
b110 *
b111 %
b111 (
b1100 $
b1100 '
