Verilog_fundamentals/Decoder/module.v
// 2-to-4 Decoder using Dataflow Modeling
module decoder_2to4 (
    input wire en,       // Enable pin (Active High)
    input wire [1:0] in, // 2-bit binary input selector
    output wire [3:0] out // 4-bit decoded output vector
);

    // Continuous assignment statements mapping decoder logic
    assign out[0] = en & (~in[1]) & (~in[0]);
    assign out[1] = en & (~in[1]) & (in[0]);
    assign out[2] = en & (in[1])  & (~in[0]);
    assign out[3] = en & (in[1])  & (in[0]);

endmodule

Verilog_fundamentals/Decoder/testbench.v
`timescale 1ns / 1ps

module decoder_2to4_tb;

    // Testbench registers (Inputs to the design under test)
    reg tb_en;
    reg [1:0] tb_in;
    
    // Testbench wires (Outputs from the design under test)
    wire [3:0] tb_out;

    // Instantiate the Device Under Test (DUT) using named port connections
    decoder_2to4 dut (
        .en(tb_en),
        .in(tb_in),
        .out(tb_out)
    );

    // Configuration block for Icarus Verilog / GTKWave 
    initial begin
        $dumpfile("decoder_simulation.vcd"); // Creates the waveform file
        $dumpvars(0, decoder_2to4_tb);        // Dumps all signals in this testbench
    end

    // Stimulus block running through all permutations
    initial begin
        // Display Terminal Header formatting 
        $display("Time\t\tEnable\tInput\tOutput");
        $display("--------------------------------------");
        
        // Monitor block auto-prints to console whenever inputs or outputs change
        $monitor("%0dns\t\t%b\t%b\t%b", $time, tb_en, tb_in, tb_out);

        // Case 1: Decoder Disabled (Outputs should remain completely 0000)
        tb_en = 0; tb_in = 2'b00; #10;
        tb_en = 0; tb_in = 2'b01; #10;
        tb_en = 0; tb_in = 2'b10; #10;
        tb_en = 0; tb_in = 2'b11; #10;

        // Case 2: Decoder Enabled (Targeted output bit transitions to active High)
        tb_en = 1; tb_in = 2'b00; #10;
        tb_en = 1; tb_in = 2'b01; #10;
        tb_en = 1; tb_in = 2'b10; #10;
        tb_en = 1; tb_in = 2'b11; #10;

        // Gracefully terminate the simulation runtime
        $finish;
    end

endmodule

Verilog_fundamentals/Decoder/decoder_simulation.vcd
$date
	Sat Sep  5 23:17:04 2026
$end
$version
	Icarus Verilog
$end
$timescale
	1ps
$end
$scope module decoder_2to4_tb $end
$var wire 4 ! tb_out [3:0] $end
$var reg 1 " tb_en $end
$var reg 2 # tb_in [1:0] $end
$scope module dut $end
$var wire 1 " en $end
$var wire 2 $ in [1:0] $end
$var wire 4 % out [3:0] $end
$upscope $end
$upscope $end
$enddefinitions $end
$comment Show the parameter values. $end
$dumpall
$end
#0
$dumpvars
b0 %
b0 $
b0 #
0"
b0 !
$end
#10000
b1 #
b1 $
#20000
b10 #
b10 $
#30000
b11 #
b11 $
#40000
b1 !
b1 %
b0 #
b0 $
1"
#50000
b10 !
b10 %
b1 #
b1 $
#60000
b100 !
b100 %
b10 #
b10 $
#70000
b1000 !
b1000 %
b11 #
b11 $
