Sequential_circuits/PISO/module.v
module piso (
    input  wire       clk,
    input  wire       reset,
    input  wire       load,
    input  wire [3:0] d,
    output wire       serial_out
);

reg [3:0] q;

always @(posedge clk or posedge reset) begin
    if (reset)
        q <= 4'b0000;
    else if (load)
        q <= d;
    else
        q <= {q[2:0], 1'b0};
end

assign serial_out = q[3];

endmodule

Sequential_circuits/PISO/testbench.v
`timescale 1ns/1ps

module tb_piso;

reg clk;
reg reset;
reg load;
reg [3:0] d;
wire serial_out;

piso uut (
    .clk(clk),
    .reset(reset),
    .load(load),
    .d(d),
    .serial_out(serial_out)
);

// Clock generation
always #5 clk = ~clk;

initial begin

    $dumpfile("piso.vcd");
    $dumpvars(0, tb_piso);

    // Initial values
    clk = 0;
    reset = 1;
    load = 0;
    d = 4'b0000;

    // Release reset
    #10 reset = 0;

    // Parallel load 1011
    #2 d = 4'b1011;
    load = 1;

    // Disable load and start shifting
    #10 load = 0;

    // Wait for all bits to shift out
    #40;

    $finish;

end

endmodule

Sequential_circuits/PISO/piso.vcd
$date
	Tue Sep 15 17:46:38 2026
$end
$version
	Icarus Verilog
$end
$timescale
	1ps
$end
$scope module tb_piso $end
$var wire 1 ! serial_out $end
$var reg 1 " clk $end
$var reg 4 # d [3:0] $end
$var reg 1 $ load $end
$var reg 1 % reset $end
$scope module uut $end
$var wire 1 " clk $end
$var wire 4 & d [3:0] $end
$var wire 1 $ load $end
$var wire 1 % reset $end
$var wire 1 ! serial_out $end
$var reg 4 ' q [3:0] $end
$upscope $end
$upscope $end
$enddefinitions $end
$comment Show the parameter values. $end
$dumpall
$end
#0
$dumpvars
b0 '
b0 &
1%
0$
b0 #
0"
0!
$end
#5000
1"
#10000
0"
0%
#12000
1$
b1011 #
b1011 &
#15000
1!
b1011 '
1"
#20000
0"
#22000
0$
#25000
0!
b110 '
1"
#30000
0"
#35000
1!
b1100 '
1"
#40000
0"
#45000
b1000 '
1"
#50000
0"
#55000
0!
b0 '
1"
