Sequential_circuits/SIPO/module.v
module sipo (
    input  wire       clk,
    input  wire       reset,
    input  wire       serial_in,
    output reg  [3:0] q
);

always @(posedge clk or posedge reset) begin
    if (reset)
        q <= 4'b0000;
    else
        q <= {q[2:0], serial_in};
end

endmodule

Sequential_circuits/SIPO/testbench.v
`timescale 1ns/1ps

module tb_sipo;

reg clk;
reg reset;
reg serial_in;
wire [3:0] q;

sipo uut (
    .clk(clk),
    .reset(reset),
    .serial_in(serial_in),
    .q(q)
);

// Clock generation
always #5 clk = ~clk;

initial begin

    $dumpfile("sipo.vcd");
    $dumpvars(0, tb_sipo);

    // Initial values
    clk = 0;
    reset = 1;
    serial_in = 0;

    // Release reset
    #10 reset = 0;

    // Send 1
    #2 serial_in = 1;

    // Send 0
    #10 serial_in = 0;

    // Send 1
    #10 serial_in = 1;

    // Send 1
    #10 serial_in = 1;

    // Send 0
    #10 serial_in = 0;

    #10 $finish;

end

endmodule

Sequential_circuits/SIPO/sipo.vcd
$date
	Tue Sep 15 17:47:24 2026
$end
$version
	Icarus Verilog
$end
$timescale
	1ps
$end
$scope module tb_sipo $end
$var wire 4 ! q [3:0] $end
$var reg 1 " clk $end
$var reg 1 # reset $end
$var reg 1 $ serial_in $end
$scope module uut $end
$var wire 1 " clk $end
$var wire 1 # reset $end
$var wire 1 $ serial_in $end
$var reg 4 % q [3:0] $end
$upscope $end
$upscope $end
$enddefinitions $end
$comment Show the parameter values. $end
$dumpall
$end
#0
$dumpvars
b0 %
0$
1#
0"
b0 !
$end
#5000
1"
#10000
0"
0#
#12000
1$
#15000
b1 !
b1 %
1"
#20000
0"
#22000
0$
#25000
b10 !
b10 %
1"
#30000
0"
#32000
1$
#35000
b101 !
b101 %
1"
#40000
0"
#45000
b1011 !
b1011 %
1"
#50000
0"
#52000
0$
#55000
b110 !
b110 %
1"
