Sequential_circuits/D_flipflop/module.v
module d_flipflop (
    input  wire D,
    input  wire CLK,
    output reg  Q,
    output reg Qbar
);

always @(posedge CLK) begin

    Q    <= D;
    Qbar <= ~D;

end

endmodule

Sequential_circuits/D_flipflop/testbench.v
`timescale 1ns/1ps

module tb_d_flipflop;

    reg D;
    reg CLK;

    wire Q;
    wire Qbar;

    // Instantiate D flip-flop
    d_flipflop uut (
        .D(D),
        .CLK(CLK),
        .Q(Q),
        .Qbar(Qbar)
    );

    // Clock generation
    initial begin
        CLK = 0;

        forever #5 CLK = ~CLK;
    end

    // Test inputs
    initial begin

        // GTKWave waveform
        $dumpfile("d_flipflop.vcd");
        $dumpvars(0, tb_d_flipflop);

        $monitor("Time=%0t | CLK=%b D=%b | Q=%b Qbar=%b",
                 $time, CLK, D, Q, Qbar);

        // Initial D
        D = 0;

        #12;

        // D = 1
        D = 1;

        #10;

        // D = 0
        D = 0;

        #10;

        // D = 1
        D = 1;

        #10;

        // D = 0
        D = 0;

        #10;

        $finish;

    end

endmodule

Sequential_circuits/D_flipflop/d_flipflop.vcd
$date
	Mon Sep 21 23:41:11 2026
$end
$version
	Icarus Verilog
$end
$timescale
	1ps
$end
$scope module tb_d_flipflop $end
$var wire 1 ! Qbar $end
$var wire 1 " Q $end
$var reg 1 # CLK $end
$var reg 1 $ D $end
$scope module uut $end
$var wire 1 # CLK $end
$var wire 1 $ D $end
$var reg 1 " Q $end
$var reg 1 ! Qbar $end
$upscope $end
$upscope $end
$enddefinitions $end
$comment Show the parameter values. $end
$dumpall
$end
#0
$dumpvars
0$
0#
x"
x!
$end
#5000
1!
0"
1#
#10000
0#
#12000
1$
#15000
0!
1"
1#
#20000
0#
#22000
0$
#25000
1!
0"
1#
#30000
0#
#32000
1$
#35000
0!
1"
1#
#40000
0#
#42000
0$
#45000
1!
0"
1#
