Sequential_circuits/Jk_flipflop/module.v
module jk_flipflop (
    input  wire J,
    input  wire K,
    input  wire CLK,
    output reg Q,
    output reg Qbar
);

always @(posedge CLK) begin

    case ({J, K})

        2'b00: begin
            Q <= Q;       // HOLD
        end

        2'b01: begin
            Q <= 1'b0;    // RESET
        end

        2'b10: begin
            Q <= 1'b1;    // SET
        end

        2'b11: begin
            Q <= ~Q;      // TOGGLE
        end

    endcase

    Qbar <= ~Q;

end

endmodule

Sequential_circuits/Jk_flipflop/testbench.v
`timescale 1ns/1ps

module tb_jk_flipflop;

    reg J;
    reg K;
    reg CLK;

    wire Q;
    wire Qbar;

    // Instantiate JK flip-flop
    jk_flipflop uut (
        .J(J),
        .K(K),
        .CLK(CLK),
        .Q(Q),
        .Qbar(Qbar)
    );

    // Clock generation
    initial begin
        CLK = 0;

        forever #5 CLK = ~CLK;
    end

    // Test inputs
    initial begin

        // GTKWave waveform
        $dumpfile("jk_flipflop.vcd");
        $dumpvars(0, tb_jk_flipflop);

        $monitor("Time=%0t | CLK=%b J=%b K=%b | Q=%b Qbar=%b",
                 $time, CLK, J, K, Q, Qbar);

        // Initial
        J = 0;
        K = 0;

        #10;

        // SET
        J = 1;
        K = 0;

        #10;

        // HOLD
        J = 0;
        K = 0;

        #10;

        // RESET
        J = 0;
        K = 1;

        #10;

        // SET
        J = 1;
        K = 0;

        #10;

        // TOGGLE
        J = 1;
        K = 1;

        #10;

        // TOGGLE again
        J = 1;
        K = 1;

        #10;

        $finish;

    end

endmodule

Sequential_circuits/Jk_flipflop/jk_flipflop.vcd
$date
	Tue Sep 22 22:09:11 2026
$end
$version
	Icarus Verilog
$end
$timescale
	1ps
$end
$scope module tb_jk_flipflop $end
$var wire 1 ! Qbar $end
$var wire 1 " Q $end
$var reg 1 # CLK $end
$var reg 1 $ J $end
$var reg 1 % K $end
$scope module uut $end
$var wire 1 # CLK $end
$var wire 1 $ J $end
$var wire 1 % K $end
$var reg 1 " Q $end
$var reg 1 ! Qbar $end
$upscope $end
$upscope $end
$enddefinitions $end
$comment Show the parameter values. $end
$dumpall
$end
#0
$dumpvars
0%
0$
0#
x"
x!
$end
#5000
1#
#10000
0#
1$
#15000
1"
1#
#20000
0#
0$
#25000
0!
1#
#30000
0#
1%
#35000
0"
1#
#40000
0#
0%
1$
#45000
1!
1"
1#
#50000
0#
1%
#55000
0!
0"
1#
#60000
0#
#65000
1!
1"
1#
