Verilog_fundamentals/Full_adder/module.v
// full_adder.v
module full_adder (
    input wire a,    // First input bit
    input wire b,    // Second input bit
    input wire cin,  // Carry-in bit
    output wire sum, // Sum output bit
    output wire cout // Carry-out output bit
);

    // Continuous assignments mapping expressions to output wires
    assign sum  = a ^ b ^ cin;
    assign cout = (a & b) | (b & cin) | (cin & a);

endmodule

Verilog_fundamentals/Full_adder/testbench.v
// full_adder_tb.v
`timescale 1ns / 1ps

module full_adder_tb;

    // Inputs are declared as registers (reg) to hold state
    reg a;
    reg b;
    reg cin;

    // Outputs are declared as wires to listen to changes from the design
    wire sum;
    wire cout;

    // Instantiate the Unit Under Test (UUT)
    full_adder uut (
        .a(a),
        .b(b),
        .cin(cin),
        .sum(sum),
        .cout(cout)
    );

    initial begin
        // Setup Icarus Verilog waveform dumping
        $dumpfile("full_adder.vcd");
        $dumpvars(0, full_adder_tb);

        // Print monitoring labels to the terminal output
        $monitor("Time=%0dns | Inputs: A=%b B=%b Cin=%b | Outputs: Sum=%b Cout=%b", 
                 $time, a, b, cin, sum, cout);

        // Apply all 8 possible binary combinations sequentially
        a = 0; b = 0; cin = 0; #10;
        a = 0; b = 0; cin = 1; #10;
        a = 0; b = 1; cin = 0; #10;
        a = 0; b = 1; cin = 1; #10;
        a = 1; b = 0; cin = 0; #10;
        a = 1; b = 0; cin = 1; #10;
        a = 1; b = 1; cin = 0; #10;
        a = 1; b = 1; cin = 1; #10;

        // Terminate the simulation cleanly
        $finish;
    end

endmodule

Verilog_fundamentals/Full_adder/full_adder.vcd
$date
	Sat Sep  5 23:21:13 2026
$end
$version
	Icarus Verilog
$end
$timescale
	1ps
$end
$scope module full_adder_tb $end
$var wire 1 ! sum $end
$var wire 1 " cout $end
$var reg 1 # a $end
$var reg 1 $ b $end
$var reg 1 % cin $end
$scope module uut $end
$var wire 1 # a $end
$var wire 1 $ b $end
$var wire 1 % cin $end
$var wire 1 " cout $end
$var wire 1 ! sum $end
$upscope $end
$upscope $end
$enddefinitions $end
$comment Show the parameter values. $end
$dumpall
$end
#0
$dumpvars
0%
0$
0#
0"
0!
$end
#10000
1!
1%
#20000
0%
1$
#30000
1"
0!
1%
#40000
0"
1!
0%
0$
1#
#50000
1"
0!
1%
#60000
0%
1$
#70000
1!
1%
