Verilog_fundamentals/7_seg_decoder/module.v
// Module: seven_seg_decoder
// Description: Dataflow implementation of a 4-bit Hex to 7-segment decoder (Common Cathode)
module seven_seg_decoder (
    input [3:0] hex_val,     // 4-bit input (0x0 to 0xF)
    output [6:0] seg         // 7-bit output representing segments {a, b, c, d, e, f, g}
);

    // Segment mapping format: {a, b, c, d, e, f, g}
    // 1 = segment ON, 0 = segment OFF (Common Cathode)
    assign seg = (hex_val == 4'h0) ? 7'b1111110 : // 0
                 (hex_val == 4'h1) ? 7'b0110000 : // 1
                 (hex_val == 4'h2) ? 7'b1101101 : // 2
                 (hex_val == 4'h3) ? 7'b1111001 : // 3
                 (hex_val == 4'h4) ? 7'b0110011 : // 4
                 (hex_val == 4'h5) ? 7'b1011011 : // 5
                 (hex_val == 4'h6) ? 7'b1011111 : // 6
                 (hex_val == 4'h7) ? 7'b1110000 : // 7
                 (hex_val == 4'h8) ? 7'b1111111 : // 8
                 (hex_val == 4'h9) ? 7'b1111011 : // 9
                 (hex_val == 4'hA) ? 7'b1110111 : // A
                 (hex_val == 4'hB) ? 7'b0011111 : // b
                 (hex_val == 4'hC) ? 7'b1001110 : // C
                 (hex_val == 4'hD) ? 7'b0111101 : // d
                 (hex_val == 4'hE) ? 7'b1001111 : // E
                 (hex_val == 4'hF) ? 7'b1000111 : // F
                                     7'b0000000;  // Default Off

endmodule

Verilog_fundamentals/7_seg_decoder/testbench.v
`timescale 1ns / 1ps

module seven_seg_decoder_tb;

    // Testbench signals
    reg [3:0] tb_hex_val;
    wire [6:0] tb_seg;
    
    // Loop variable
    integer i;

    // Instantiate Unit Under Test (UUT)
    seven_seg_decoder uut (
        .hex_val(tb_hex_val),
        .seg(tb_seg)
    );

    initial begin
        // Setup value change dump (.vcd) files for GTKWave visualization
        $dumpfile("seven_seg_simulation.vcd");
        $dumpvars(0, seven_seg_decoder_tb);
        
        // Print header console display
        $display("Time\tInput(Hex)\tSegments(abcdefg)");
        $monitor("%0d\t%h\t\t%b", $time, tb_hex_val, tb_seg);

        // Iterate through all 16 possible values (0 to 15)
        for (i = 0; i < 16; i = i + 1) begin
            tb_hex_val = i;
            #10; // Wait 10 time units per vector
        end

        // End the simulation execution
        $finish;
    end

endmodule

Verilog_fundamentals/7_seg_decoder/seven_seg_simulation.vcd
$date
	Sun Sep  6 00:25:54 2026
$end
$version
	Icarus Verilog
$end
$timescale
	1ps
$end
$scope module seven_seg_decoder_tb $end
$var wire 7 ! tb_seg [6:0] $end
$var reg 4 " tb_hex_val [3:0] $end
$var integer 32 # i [31:0] $end
$scope module uut $end
$var wire 4 $ hex_val [3:0] $end
$var wire 7 % seg [6:0] $end
$upscope $end
$upscope $end
$enddefinitions $end
$comment Show the parameter values. $end
$dumpall
$end
#0
$dumpvars
b1111110 %
b0 $
b0 #
b0 "
b1111110 !
$end
#10000
b110000 !
b110000 %
b1 "
b1 $
b1 #
#20000
b1101101 !
b1101101 %
b10 "
b10 $
b10 #
#30000
b1111001 !
b1111001 %
b11 "
b11 $
b11 #
#40000
b110011 !
b110011 %
b100 "
b100 $
b100 #
#50000
b1011011 !
b1011011 %
b101 "
b101 $
b101 #
#60000
b1011111 !
b1011111 %
b110 "
b110 $
b110 #
#70000
b1110000 !
b1110000 %
b111 "
b111 $
b111 #
#80000
b1111111 !
b1111111 %
b1000 "
b1000 $
b1000 #
#90000
b1111011 !
b1111011 %
b1001 "
b1001 $
b1001 #
#100000
b1110111 !
b1110111 %
b1010 "
b1010 $
b1010 #
#110000
b11111 !
b11111 %
b1011 "
b1011 $
b1011 #
#120000
b1001110 !
b1001110 %
b1100 "
b1100 $
b1100 #
#130000
b111101 !
b111101 %
b1101 "
b1101 $
b1101 #
#140000
b1001111 !
b1001111 %
b1110 "
b1110 $
b1110 #
#150000
b1000111 !
b1000111 %
b1111 "
b1111 $
b1111 #
#160000
b10000 #
