Verilog_fundamentals/Priority_encoder/module.v
module priority_encoder_df (
    input wire [3:0] in,
    output wire [1:0] out,
    output wire idle
);

    // Idle is high only when all 4 input bits are zero
    assign idle = (in == 4'b0000);

    // Conditional dataflow nesting: highest bit (3) down to lowest bit (1)
    assign out = (in[3]) ? 2'b11 :
                 (in[2]) ? 2'b10 :
                 (in[1]) ? 2'b01 : 2'b00;

endmodule

Verilog_fundamentals/Priority_encoder/testbench.v
`timescale 1ns / 1ps

module tb_priority_encoder_df;

    // Inputs are declared as registers to hold vectors
    reg [3:0] in;

    // Outputs are declared as wires to capture dataflow driven values
    wire [1:0] out;
    wire idle;

    // Loop variable declared as integer for test stimulation
    integer i;

    // Instantiate the Device Under Test (DUT)
    priority_encoder_df uut (
        .in(in),
        .out(out),
        .idle(idle)
    );

    // Monitor changes automatically in the terminal
    initial begin
        $monitor("Time = %0t ns | Input [3:0] = %b | Output [1:0] = %b | Idle = %b", $time, in, out, idle);
    end

    // Stimulus block running a complete exhaustive test
    initial begin
        // Dump waveforms for viewing in GTKWave
        $dumpfile("priority_df_waveform.vcd");
        $dumpvars(0, tb_priority_encoder_df);

        // Loop from 0 up to 15 (all 16 input conditions)
        for (i = 0; i < 16; i = i + 1) begin
            in = i;
            #10; // Wait 10 time units between changes
        end

        // End the simulation
        $finish;
    end

endmodule

Verilog_fundamentals/Priority_encoder/priority_df_waveform.vcd
$date
	Sat Sep  5 23:52:43 2026
$end
$version
	Icarus Verilog
$end
$timescale
	1ps
$end
$scope module tb_priority_encoder_df $end
$var wire 2 ! out [1:0] $end
$var wire 1 " idle $end
$var reg 4 # in [3:0] $end
$var integer 32 $ i [31:0] $end
$scope module uut $end
$var wire 4 % in [3:0] $end
$var wire 2 & out [1:0] $end
$var wire 1 " idle $end
$upscope $end
$upscope $end
$enddefinitions $end
$comment Show the parameter values. $end
$dumpall
$end
#0
$dumpvars
b0 &
b0 %
b0 $
b0 #
1"
b0 !
$end
#10000
0"
b1 #
b1 %
b1 $
#20000
b1 !
b1 &
b10 #
b10 %
b10 $
#30000
b11 #
b11 %
b11 $
#40000
b10 !
b10 &
b100 #
b100 %
b100 $
#50000
b101 #
b101 %
b101 $
#60000
b110 #
b110 %
b110 $
#70000
b111 #
b111 %
b111 $
#80000
b11 !
b11 &
b1000 #
b1000 %
b1000 $
#90000
b1001 #
b1001 %
b1001 $
#100000
b1010 #
b1010 %
b1010 $
#110000
b1011 #
b1011 %
b1011 $
#120000
b1100 #
b1100 %
b1100 $
#130000
b1101 #
b1101 %
b1101 $
#140000
b1110 #
b1110 %
b1110 $
#150000
b1111 #
b1111 %
b1111 $
#160000
b10000 $
