Sequential_circuits/PIPO/module.v
module pipo (
    input  wire       clk,
    input  wire       reset,
    input  wire [3:0] d,
    output reg  [3:0] q
);

always @(posedge clk or posedge reset) begin
    if (reset)
        q <= 4'b0000;
    else
        q <= d;
end

endmodule

Sequential_circuits/PIPO/testbench.v
`timescale 1ns/1ps

module tb_pipo;

reg clk;
reg reset;
reg [3:0] d;
wire [3:0] q;

pipo uut (
    .clk(clk),
    .reset(reset),
    .d(d),
    .q(q)
);

// Clock generation
always #5 clk = ~clk;

initial begin

    $dumpfile("pipo.vcd");
    $dumpvars(0, tb_pipo);

    // Initial values
    clk = 0;
    reset = 1;
    d = 4'b0000;

    // Release reset
    #10 reset = 0;

    // Parallel input
    #2 d = 4'b1010;

    #10 d = 4'b1100;

    #10 d = 4'b0111;

    #10 d = 4'b1001;

    #10 $finish;

end

endmodule

Sequential_circuits/PIPO/pipo.vcd
$date
	Tue Sep 15 17:45:17 2026
$end
$version
	Icarus Verilog
$end
$timescale
	1ps
$end
$scope module tb_pipo $end
$var wire 4 ! q [3:0] $end
$var reg 1 " clk $end
$var reg 4 # d [3:0] $end
$var reg 1 $ reset $end
$scope module uut $end
$var wire 1 " clk $end
$var wire 4 % d [3:0] $end
$var wire 1 $ reset $end
$var reg 4 & q [3:0] $end
$upscope $end
$upscope $end
$enddefinitions $end
$comment Show the parameter values. $end
$dumpall
$end
#0
$dumpvars
b0 &
b0 %
1$
b0 #
0"
b0 !
$end
#5000
1"
#10000
0"
0$
#12000
b1010 #
b1010 %
#15000
b1010 !
b1010 &
1"
#20000
0"
#22000
b1100 #
b1100 %
#25000
b1100 !
b1100 &
1"
#30000
0"
#32000
b111 #
b111 %
#35000
b111 !
b111 &
1"
#40000
0"
#42000
b1001 #
b1001 %
#45000
b1001 !
b1001 &
1"
