Always_blck/BCD_Excess3/module.v
module bcd_excess3 (
    input  wire [3:0] bcd,
    output reg  [3:0] excess3
);

always @(*) begin

    case (bcd)

        4'b0000: excess3 = 4'b0011; // 0 -> 3
        4'b0001: excess3 = 4'b0100; // 1 -> 4
        4'b0010: excess3 = 4'b0101; // 2 -> 5
        4'b0011: excess3 = 4'b0110; // 3 -> 6
        4'b0100: excess3 = 4'b0111; // 4 -> 7
        4'b0101: excess3 = 4'b1000; // 5 -> 8
        4'b0110: excess3 = 4'b1001; // 6 -> 9
        4'b0111: excess3 = 4'b1010; // 7 -> 10
        4'b1000: excess3 = 4'b1011; // 8 -> 11
        4'b1001: excess3 = 4'b1100; // 9 -> 12

        // Invalid BCD inputs: 10-15
        default: excess3 = 4'bxxxx;

    endcase

end

endmodule

Always_blck/BCD_Excess3/testbench.v
`timescale 1ns/1ps

module bcd_excess3_tb;

    reg  [3:0] bcd;
    wire [3:0] excess3;

    // Instantiate DUT
    bcd_excess3 uut (
        .bcd(bcd),
        .excess3(excess3)
    );

    initial begin

        // Create waveform file
        $dumpfile("bcd_excess3.vcd");
        $dumpvars(0, bcd_excess3_tb);

        $monitor("Time=%0t | BCD=%b | Excess-3=%b",
                 $time, bcd, excess3);

        // Test 0
        bcd = 4'b0000;
        #10;

        // Test 1
        bcd = 4'b0001;
        #10;

        // Test 2
        bcd = 4'b0010;
        #10;

        // Test 3
        bcd = 4'b0011;
        #10;

        // Test 4
        bcd = 4'b0100;
        #10;

        // Test 5
        bcd = 4'b0101;
        #10;

        // Test 6
        bcd = 4'b0110;
        #10;

        // Test 7
        bcd = 4'b0111;
        #10;

        // Test 8
        bcd = 4'b1000;
        #10;

        // Test 9
        bcd = 4'b1001;
        #10;

        // Test invalid BCD
        bcd = 4'b1010;
        #10;

        $finish;

    end

endmodule

Always_blck/BCD_Excess3/bcd_excess3.vcd
$date
	Mon Sep  7 23:09:43 2026
$end
$version
	Icarus Verilog
$end
$timescale
	1ps
$end
$scope module bcd_excess3_tb $end
$var wire 4 ! excess3 [3:0] $end
$var reg 4 " bcd [3:0] $end
$scope module uut $end
$var wire 4 # bcd [3:0] $end
$var reg 4 $ excess3 [3:0] $end
$upscope $end
$upscope $end
$enddefinitions $end
$comment Show the parameter values. $end
$dumpall
$end
#0
$dumpvars
b11 $
b0 #
b0 "
b11 !
$end
#10000
b100 !
b100 $
b1 "
b1 #
#20000
b101 !
b101 $
b10 "
b10 #
#30000
b110 !
b110 $
b11 "
b11 #
#40000
b111 !
b111 $
b100 "
b100 #
#50000
b1000 !
b1000 $
b101 "
b101 #
#60000
b1001 !
b1001 $
b110 "
b110 #
#70000
b1010 !
b1010 $
b111 "
b111 #
#80000
b1011 !
b1011 $
b1000 "
b1000 #
#90000
b1100 !
b1100 $
b1001 "
b1001 #
#100000
bx !
bx $
b1010 "
b1010 #
